depthy/__init__.py
depthy/bin/cli.py
depthy/lightfield/__init__.py
depthy/lightfield/epi_depth.py
depthy/lightfield/structure_tensor.py
depthy/misc/__init__.py
depthy/misc/data_downloader.py
depthy/misc/io_functions.py
depthy/misc/normalizer.py
depthy/misc/pfm_handler.py
depthy/misc/plots.py
depthy/misc/ply_handler.py
depthy/misc/primal_dual.py
depthy/stereo/__init__.py
depthy/stereo/cost_aggregation.py
depthy/stereo/dissimilarity_measures.py
depthy/stereo/feature_methods.py
depthy/stereo/helper_funs.py
depthy/stereo/sad_block_matching.py
depthy/stereo/semi_global_matching.py
depthy-0.4.0.data/scripts/cli.py
tests/__init__.py
tests/test_all.py
tests/test_cli.py
tests/test_epi_depth.py
tests/test_plt.py
tests/test_stereo.py
tests/test_structure_tensor.py
depthy-0.4.0.dist-info/METADATA
depthy-0.4.0.dist-info/WHEEL
depthy-0.4.0.dist-info/entry_points.txt
depthy-0.4.0.dist-info/top_level.txt
depthy-0.4.0.dist-info/RECORD
