Metadata-Version: 2.1
Name: depthy
Version: 0.4.0
Summary: Package enabling depth computation
Home-page: http://github.com/hahnec/depthy
Author: Christopher Hahne
Author-email: inbox@christopherhahne.de
License: GNU GPL V3.0
Keywords: depth light-field lightfield epipolar epi optimization
Platform: UNKNOWN
Requires-Python: >=3
Requires-Dist: numpy
Requires-Dist: scipy
Requires-Dist: imageio
Requires-Dist: matplotlib
Requires-Dist: requests
Requires-Dist: docutils
